odoo/addons/partner_vat_unique/README.rst
odoo/addons/partner_vat_unique/__init__.py
odoo/addons/partner_vat_unique/__manifest__.py
odoo/addons/partner_vat_unique/i18n/es.po
odoo/addons/partner_vat_unique/i18n/partner_vat_unique.pot
odoo/addons/partner_vat_unique/models/__init__.py
odoo/addons/partner_vat_unique/models/res_partner.py
odoo/addons/partner_vat_unique/static/description/icon.png
odoo/addons/partner_vat_unique/tests/__init__.py
odoo/addons/partner_vat_unique/tests/test_vat_unique.py
odoo11_addon_partner_vat_unique-11.0.1.0.4.dist-info/METADATA
odoo11_addon_partner_vat_unique-11.0.1.0.4.dist-info/WHEEL
odoo11_addon_partner_vat_unique-11.0.1.0.4.dist-info/top_level.txt
odoo11_addon_partner_vat_unique-11.0.1.0.4.dist-info/RECORD
